README.rst
setup.py
dumpyme.egg-info/PKG-INFO
dumpyme.egg-info/SOURCES.txt
dumpyme.egg-info/dependency_links.txt
dumpyme.egg-info/entry_points.txt
dumpyme.egg-info/pbr.json
dumpyme.egg-info/requires.txt
dumpyme.egg-info/top_level.txt
src/__init__.py
src/commander.py
src/dumpyme.py
src/tasks/__init__.py
src/tasks/executor.py
src/templates/tmp_dumpyme.ini
src/utils/__init__.py
src/utils/config.py
src/utils/reader.py
src/utils/supported_databases.py