Metadata-Version: 1.0
Name: dumpyme
Version: 0.0.9
Summary: Command line package to get dump databases
Home-page: https://github.com/marioidival/dumpyme
Author: Mario Idival
Author-email: marioidival@gmail.com
License: MIT
Keywords: dump dumpyme mongodb postgres mysql databases
Platform: UNKNOWN
